atonal/__init__.py
atonal/base.py
atonal/tests/__init__.py
atonal/tests/test_chordspace.py
atonal-0.0.7.dist-info/METADATA
atonal-0.0.7.dist-info/WHEEL
atonal-0.0.7.dist-info/licenses/LICENSE
atonal-0.0.7.dist-info/RECORD
