Metadata-Version: 2.4
Name: atonal
Version: 0.0.7
Summary: Tools for atonal theory -- pitch class sets, forte numbers etc.
Project-URL: Homepage, https://github.com/thorwhalen/atonal
Project-URL: Repository, https://github.com/thorwhalen/atonal
Project-URL: Documentation, https://thorwhalen.github.io/atonal
Author: Thor Whalen
License: mit
License-File: LICENSE
Requires-Python: >=3.10
Requires-Dist: pandas
Requires-Dist: tonal
Provides-Extra: dev
Requires-Dist: pytest-cov>=4.0; extra == 'dev'
Requires-Dist: pytest>=7.0; extra == 'dev'
Requires-Dist: ruff>=0.1.0; extra == 'dev'
Provides-Extra: docs
Requires-Dist: sphinx-rtd-theme>=1.0; extra == 'docs'
Requires-Dist: sphinx>=6.0; extra == 'docs'
